{
  "$schema": "../gen/schemas/desktop-schema.json",
  "identifier": "default",
  "description": "Capability for the main window",
  "windows": ["main"],
  "permissions": [
    "core:default",
    "opener:default",
    {
      "identifier": "shell:allow-spawn",
      "allow": [
        {
          "name": "binaries/llama-server",
          "sidecar": true,
          "args": true
        }
      ]
    },
    "core:window:allow-set-size",
    "core:window:allow-set-position",
    "core:window:allow-start-dragging",
    "core:window:allow-close",
    "global-shortcut:allow-is-registered",
    "global-shortcut:allow-register",
    "global-shortcut:allow-unregister",
    "clipboard-manager:allow-read-text",
    "clipboard-manager:default",
    "dialog:allow-open"
  ]
}
